MANIFEST.in
README.md
setup.cfg
setup.py
marsDemonstrator/__init__.py
marsDemonstrator.egg-info/PKG-INFO
marsDemonstrator.egg-info/SOURCES.txt
marsDemonstrator.egg-info/dependency_links.txt
marsDemonstrator.egg-info/requires.txt
marsDemonstrator.egg-info/top_level.txt
marsDemonstrator/designMethods/__init__.py
marsDemonstrator/designMethods/en_13001_3_3/__init__.py
marsDemonstrator/designMethods/en_13001_3_3/computation.py
marsDemonstrator/designMethods/en_13001_3_3/en_input.py
marsDemonstrator/designMethods/en_13001_3_3/gp_input.py
marsDemonstrator/designMethods/en_13001_3_3/gpytorchModels.py
marsDemonstrator/designMethods/en_13001_3_3/input_error_check.py
marsDemonstrator/designMethods/en_13001_3_3/input_scale.pkl
marsDemonstrator/designMethods/en_13001_3_3/learners.pkl
marsDemonstrator/designMethods/en_13001_3_3/load_collective.py
marsDemonstrator/designMethods/en_13001_3_3/mars_input.py
marsDemonstrator/main_app/__init__.py
marsDemonstrator/main_app/main_functions.py
marsDemonstrator/main_app/output.py