Metadata-Version: 1.2
Name: marsDemonstrator
Version: 0.1.5
Summary: This package contains the demonstrator for the project mars.
Home-page: UNKNOWN
Author: Mathias Laile
Author-email: mathias.laile@tum.de
License: UNKNOWN
Platform: UNKNOWN
Classifier: License :: CC0 1.0 Universal (CC0 1.0) Public Domain Dedication
